[
  {
    "con0": 1,
    "ext0": 0,
    "con1": 1,
    "x": 4,
    "y": 6,
    "ext3": 0,
    "con2": 1,
    "ext2": 0,
    "ext1": 0,
    "con3": 1
  },
  {
    "con0": 1,
    "ext0": 0,
    "con1": 1,
    "x": 6,
    "y": 6,
    "ext3": 0,
    "con2": 1,
    "ext2": 0,
    "ext1": 0,
    "con3": 1
  },
  {
    "con0": 1,
    "ext0": 0,
    "con1": 1,
    "x": 6,
    "y": 4,
    "ext3": 0,
    "con2": 1,
    "ext2": 0,
    "ext1": 0,
    "con3": 1
  },
  {
    "con0": 1,
    "ext0": 0,
    "con1": 1,
    "x": 4,
    "y": 4,
    "ext3": 0,
    "con2": 1,
    "ext2": 0,
    "ext1": 0,
    "con3": 1
  }
]