[{"con3":-1,"con2":1,"ext1":-1,"ext2":0,"ext3":-1,"ext0":0,"con0":1,"y":30,"con1":-1,"x":2},{"con3":-1,"con2":1,"ext1":-1,"ext2":0,"ext3":-1,"ext0":0,"con0":1,"y":31,"con1":-1,"x":2},{"con3":-1,"con2":1,"ext1":-1,"ext2":0,"ext3":-1,"ext0":0,"con0":1,"y":29,"con1":-1,"x":2},{"con3":-1,"con2":1,"ext1":-1,"ext2":0,"ext3":-1,"ext0":0,"con0":1,"y":32,"con1":-1,"x":2},{"con3":-1,"con2":1,"ext1":-1,"ext2":0,"ext3":-1,"ext0":0,"con0":1,"y":28,"con1":-1,"x":2},{"con3":-1,"con2":1,"ext1":-1,"ext2":0,"ext3":-1,"ext0":0,"con0":1,"y":33,"con1":-1,"x":2},{"con3":-1,"con2":1,"ext1":-1,"ext2":0,"ext3":-1,"ext0":0,"con0":1,"y":27,"con1":-1,"x":2},{"con3":-1,"con2":1,"ext1":-1,"ext2":0,"ext3":-1,"ext0":0,"con0":1,"y":34,"con1":-1,"x":2},{"con3":-1,"con2":1,"ext1":-1,"ext2":0,"ext3":-1,"ext0":0,"con0":1,"y":26,"con1":-1,"x":2},{"con3":-1,"con2":1,"ext1":-1,"ext2":0,"ext3":-1,"ext0":0,"con0":1,"y":35,"con1":-1,"x":2},{"con3":-1,"con2":1,"ext1":-1,"ext2":0,"ext3":-1,"ext0":0,"con0":1,"y":25,"con1":-1,"x":2},{"con3":-1,"con2":1,"ext1":-1,"ext2":0,"ext3":-1,"ext0":1,"con0":1,"y":36,"con1":-1,"x":2},{"con3":-1,"con2":1,"ext1":-1,"ext2":0,"ext3":-1,"ext0":0,"con0":1,"y":24,"con1":-1,"x":2},{"con3":1,"con2":1,"ext1":1,"ext2":1,"ext3":1,"ext0":-1,"con0":-1,"y":38,"con1":1,"x":2},{"con3":-1,"con2":1,"ext1":-1,"ext2":0,"ext3":-1,"ext0":0,"con0":1,"y":23,"con1":-1,"x":2},{"con3":1,"con2":-1,"ext1":1,"ext2":-1,"ext3":1,"ext0":-1,"con0":-1,"y":38,"con1":1,"x":4},{"con3":-1,"con2":1,"ext1":1,"ext2":1,"ext3":-1,"ext0":-1,"con0":-1,"y":38,"con1":1,"x":0},{"con3":-1,"con2":1,"ext1":-1,"ext2":0,"ext3":-1,"ext0":0,"con0":1,"y":22,"con1":-1,"x":2},{"con3":1,"con2":-1,"ext1":1,"ext2":-1,"ext3":1,"ext0":-1,"con0":-1,"y":38,"con1":1,"x":6},{"con3":-1,"con2":1,"ext1":-1,"ext2":1,"ext3":-1,"ext0":1,"con0":1,"y":36,"con1":-1,"x":0},{"con3":-1,"con2":1,"ext1":-1,"ext2":0,"ext3":-1,"ext0":0,"con0":1,"y":21,"con1":-1,"x":2},{"con3":1,"con2":-1,"ext1":1,"ext2":-1,"ext3":1,"ext0":-1,"con0":-1,"y":38,"con1":1,"x":8},{"con3":-1,"con2":1,"ext1":-1,"ext2":1,"ext3":-1,"ext0":1,"con0":1,"y":34,"con1":-1,"x":0},{"con3":-1,"con2":1,"ext1":-1,"ext2":0,"ext3":-1,"ext0":0,"con0":1,"y":20,"con1":-1,"x":2},{"con3":1,"con2":-1,"ext1":1,"ext2":-1,"ext3":1,"ext0":-1,"con0":-1,"y":38,"con1":1,"x":10},{"con3":-1,"con2":1,"ext1":-1,"ext2":1,"ext3":-1,"ext0":1,"con0":1,"y":32,"con1":-1,"x":0},{"con3":-1,"con2":1,"ext1":-1,"ext2":0,"ext3":-1,"ext0":0,"con0":1,"y":19,"con1":-1,"x":2},{"con3":1,"con2":-1,"ext1":1,"ext2":-1,"ext3":1,"ext0":-1,"con0":-1,"y":38,"con1":1,"x":12},{"con3":-1,"con2":1,"ext1":-1,"ext2":1,"ext3":-1,"ext0":1,"con0":1,"y":30,"con1":-1,"x":0},{"con3":-1,"con2":-1,"ext1":-1,"ext2":-1,"ext3":-1,"ext0":0,"con0":1,"y":18,"con1":-1,"x":2},{"con3":1,"con2":-1,"ext1":1,"ext2":-1,"ext3":1,"ext0":-1,"con0":-1,"y":38,"con1":1,"x":14},{"con3":-1,"con2":1,"ext1":-1,"ext2":1,"ext3":-1,"ext0":1,"con0":1,"y":28,"con1":-1,"x":0},{"con3":1,"con2":-1,"ext1":1,"ext2":-1,"ext3":1,"ext0":-1,"con0":-1,"y":38,"con1":1,"x":16},{"con3":-1,"con2":1,"ext1":-1,"ext2":1,"ext3":-1,"ext0":1,"con0":1,"y":26,"con1":-1,"x":0},{"con3":1,"con2":-1,"ext1":1,"ext2":-1,"ext3":1,"ext0":-1,"con0":-1,"y":38,"con1":1,"x":18},{"con3":-1,"con2":1,"ext1":-1,"ext2":1,"ext3":-1,"ext0":1,"con0":1,"y":24,"con1":-1,"x":0},{"con3":1,"con2":1,"ext1":1,"ext2":1,"ext3":1,"ext0":-1,"con0":-1,"y":38,"con1":1,"x":20},{"con3":-1,"con2":1,"ext1":-1,"ext2":1,"ext3":-1,"ext0":1,"con0":1,"y":22,"con1":-1,"x":0},{"con3":1,"con2":1,"ext1":-1,"ext2":1,"ext3":1,"ext0":-1,"con0":-1,"y":38,"con1":-1,"x":22},{"con3":-1,"con2":1,"ext1":1,"ext2":1,"ext3":-1,"ext0":1,"con0":1,"y":36,"con1":1,"x":20},{"con3":-1,"con2":1,"ext1":-1,"ext2":1,"ext3":-1,"ext0":1,"con0":1,"y":20,"con1":-1,"x":0},{"con3":1,"con2":1,"ext1":-1,"ext2":1,"ext3":1,"ext0":1,"con0":1,"y":36,"con1":-1,"x":22},{"con3":-1,"con2":1,"ext1":1,"ext2":1,"ext3":-1,"ext0":1,"con0":1,"y":34,"con1":1,"x":20},{"con3":-1,"con2":1,"ext1":-1,"ext2":1,"ext3":-1,"ext0":1,"con0":1,"y":18,"con1":-1,"x":0},{"con3":1,"con2":1,"ext1":-1,"ext2":1,"ext3":1,"ext0":1,"con0":1,"y":34,"con1":-1,"x":22},{"con3":-1,"con2":1,"ext1":1,"ext2":1,"ext3":-1,"ext0":1,"con0":1,"y":32,"con1":1,"x":20},{"con3":-1,"con2":1,"ext1":-1,"ext2":1,"ext3":-1,"ext0":1,"con0":1,"y":16,"con1":-1,"x":0},{"con3":1,"con2":1,"ext1":-1,"ext2":1,"ext3":1,"ext0":1,"con0":1,"y":32,"con1":-1,"x":22},{"con3":-1,"con2":1,"ext1":1,"ext2":1,"ext3":-1,"ext0":1,"con0":1,"y":30,"con1":1,"x":20},{"con3":-1,"con2":1,"ext1":-1,"ext2":1,"ext3":-1,"ext0":1,"con0":1,"y":14,"con1":-1,"x":0},{"con3":1,"con2":1,"ext1":-1,"ext2":1,"ext3":1,"ext0":1,"con0":1,"y":30,"con1":-1,"x":22},{"con3":-1,"con2":1,"ext1":1,"ext2":1,"ext3":-1,"ext0":1,"con0":1,"y":28,"con1":1,"x":20},{"con3":-1,"con2":1,"ext1":-1,"ext2":1,"ext3":-1,"ext0":1,"con0":1,"y":12,"con1":-1,"x":0},{"con3":1,"con2":1,"ext1":-1,"ext2":1,"ext3":1,"ext0":1,"con0":1,"y":28,"con1":-1,"x":22},{"con3":-1,"con2":1,"ext1":1,"ext2":1,"ext3":-1,"ext0":1,"con0":1,"y":26,"con1":1,"x":20},{"con3":-1,"con2":1,"ext1":-1,"ext2":1,"ext3":-1,"ext0":1,"con0":1,"y":10,"con1":-1,"x":0},{"con3":1,"con2":1,"ext1":-1,"ext2":1,"ext3":1,"ext0":1,"con0":1,"y":26,"con1":-1,"x":22},{"con3":-1,"con2":1,"ext1":1,"ext2":1,"ext3":-1,"ext0":1,"con0":1,"y":24,"con1":1,"x":20},{"con3":-1,"con2":1,"ext1":-1,"ext2":1,"ext3":-1,"ext0":1,"con0":1,"y":8,"con1":-1,"x":0},{"con3":1,"con2":1,"ext1":-1,"ext2":1,"ext3":1,"ext0":1,"con0":1,"y":24,"con1":-1,"x":22},{"con3":-1,"con2":1,"ext1":1,"ext2":1,"ext3":-1,"ext0":1,"con0":1,"y":22,"con1":1,"x":20},{"con3":-1,"con2":1,"ext1":-1,"ext2":1,"ext3":-1,"ext0":1,"con0":1,"y":6,"con1":-1,"x":0},{"con3":1,"con2":1,"ext1":-1,"ext2":1,"ext3":1,"ext0":1,"con0":1,"y":22,"con1":-1,"x":22},{"con3":-1,"con2":1,"ext1":1,"ext2":1,"ext3":-1,"ext0":1,"con0":1,"y":20,"con1":1,"x":20},{"con3":-1,"con2":1,"ext1":-1,"ext2":1,"ext3":-1,"ext0":1,"con0":1,"y":4,"con1":-1,"x":0},{"con3":1,"con2":1,"ext1":-1,"ext2":1,"ext3":1,"ext0":1,"con0":1,"y":20,"con1":-1,"x":22},{"con3":1,"con2":1,"ext1":1,"ext2":1,"ext3":1,"ext0":1,"con0":1,"y":18,"con1":1,"x":20},{"con3":-1,"con2":1,"ext1":-1,"ext2":1,"ext3":-1,"ext0":1,"con0":1,"y":2,"con1":-1,"x":0},{"con3":1,"con2":1,"ext1":-1,"ext2":1,"ext3":1,"ext0":1,"con0":1,"y":18,"con1":-1,"x":22},{"con3":-1,"con2":1,"ext1":1,"ext2":1,"ext3":-1,"ext0":1,"con0":1,"y":16,"con1":1,"x":20},{"con3":1,"con2":-1,"ext1":1,"ext2":-1,"ext3":1,"ext0":-1,"con0":-1,"y":18,"con1":1,"x":18},{"con3":-1,"con2":-1,"ext1":-1,"ext2":-1,"ext3":-1,"ext0":1,"con0":1,"y":0,"con1":-1,"x":0},{"con3":1,"con2":1,"ext1":-1,"ext2":1,"ext3":1,"ext0":1,"con0":1,"y":16,"con1":-1,"x":22},{"con3":-1,"con2":1,"ext1":1,"ext2":1,"ext3":-1,"ext0":1,"con0":1,"y":14,"con1":1,"x":20},{"con3":1,"con2":-1,"ext1":1,"ext2":-1,"ext3":1,"ext0":-1,"con0":-1,"y":18,"con1":1,"x":16},{"con3":1,"con2":1,"ext1":-1,"ext2":1,"ext3":1,"ext0":1,"con0":1,"y":14,"con1":-1,"x":22},{"con3":-1,"con2":1,"ext1":1,"ext2":1,"ext3":-1,"ext0":1,"con0":1,"y":12,"con1":1,"x":20},{"con3":1,"con2":-1,"ext1":1,"ext2":-1,"ext3":1,"ext0":-1,"con0":-1,"y":18,"con1":1,"x":14},{"con3":1,"con2":1,"ext1":-1,"ext2":1,"ext3":1,"ext0":1,"con0":1,"y":12,"con1":-1,"x":22},{"con3":-1,"con2":1,"ext1":1,"ext2":1,"ext3":-1,"ext0":1,"con0":1,"y":10,"con1":1,"x":20},{"con3":1,"con2":-1,"ext1":1,"ext2":-1,"ext3":1,"ext0":-1,"con0":-1,"y":18,"con1":1,"x":12},{"con3":1,"con2":1,"ext1":-1,"ext2":1,"ext3":1,"ext0":1,"con0":1,"y":10,"con1":-1,"x":22},{"con3":-1,"con2":1,"ext1":1,"ext2":1,"ext3":-1,"ext0":1,"con0":1,"y":8,"con1":1,"x":20},{"con3":1,"con2":-1,"ext1":1,"ext2":-1,"ext3":1,"ext0":-1,"con0":-1,"y":18,"con1":1,"x":10},{"con3":1,"con2":1,"ext1":-1,"ext2":1,"ext3":1,"ext0":1,"con0":1,"y":8,"con1":-1,"x":22},{"con3":-1,"con2":1,"ext1":1,"ext2":1,"ext3":-1,"ext0":1,"con0":1,"y":6,"con1":1,"x":20},{"con3":1,"con2":-1,"ext1":1,"ext2":-1,"ext3":1,"ext0":-1,"con0":-1,"y":18,"con1":1,"x":8},{"con3":1,"con2":1,"ext1":-1,"ext2":1,"ext3":1,"ext0":1,"con0":1,"y":6,"con1":-1,"x":22},{"con3":-1,"con2":1,"ext1":1,"ext2":1,"ext3":-1,"ext0":1,"con0":1,"y":4,"con1":1,"x":20},{"con3":1,"con2":-1,"ext1":1,"ext2":-1,"ext3":1,"ext0":-1,"con0":-1,"y":18,"con1":1,"x":6},{"con3":1,"con2":1,"ext1":-1,"ext2":1,"ext3":1,"ext0":1,"con0":1,"y":4,"con1":-1,"x":22},{"con3":-1,"con2":1,"ext1":1,"ext2":1,"ext3":-1,"ext0":1,"con0":1,"y":2,"con1":1,"x":20},{"con3":-1,"con2":-1,"ext1":1,"ext2":-1,"ext3":-1,"ext0":-1,"con0":-1,"y":18,"con1":1,"x":4},{"con3":1,"con2":1,"ext1":-1,"ext2":1,"ext3":1,"ext0":1,"con0":1,"y":2,"con1":-1,"x":22},{"con3":-1,"con2":-1,"ext1":1,"ext2":-1,"ext3":-1,"ext0":1,"con0":1,"y":0,"con1":1,"x":20},{"con3":1,"con2":-1,"ext1":-1,"ext2":-1,"ext3":1,"ext0":1,"con0":1,"y":0,"con1":-1,"x":22}]